hadata/__init__.py
hadata/answer.py
hadata/assessment.py
hadata/job.py
hadata/meta.py
hadata/user.py
hareqres/__init__.py
hareqres/assessments.py
hareqres/job.py
hareqres/jwtbearer.py
hareqres/meta.py
hareqres/question.py
hareqres/user.py
hareqres/request/__init__.py
hareqres/request/assessments.py
hareqres/request/job.py
hareqres/response/__init__.py
hareqres/response/assessments.py
hareqres/response/misc.py
hareqres/response/user.py
hatest/__init__.py
hatest/mailtest.py
hautils/__init__.py
hautils/av.py
hautils/aws.py
hautils/deque.py
hautils/ha_secrets.py
hautils/hamail.py
hautils/health.py
hautils/logger.py
hautils/missconfig.py
hautils/mongo.py
hautils/rmq.py
hautils/s3.py
hautils/slack.py
hautils/utils.py
hautils/web.py
hadata-2.5.120.dist-info/LICENSE
hadata-2.5.120.dist-info/METADATA
hadata-2.5.120.dist-info/WHEEL
hadata-2.5.120.dist-info/top_level.txt
hadata-2.5.120.dist-info/RECORD
