Metadata-Version: 2.1
Name: hadata
Version: 2.5.120
Summary: HiAcuity common Data Models
Home-page: https://github.com/hiacuity/ha-data
Author: Nayana Hettiarachchi
Author-email: nayana@hiacuity.com
License: BSD 2-clause
Platform: UNKNOWN
Classifier: Programming Language :: Python :: 3.10
License-File: LICENSE
Requires-Dist: mongoengine (==0.24.2)
Requires-Dist: pydantic (==1.10.2)
Requires-Dist: boto3 (~=1.25.3)
Requires-Dist: botocore (~=1.28.3)
Requires-Dist: python-dotenv (~=0.21.0)
Requires-Dist: pika (~=1.3.1)
Requires-Dist: ddtrace (==1.5.3)
Requires-Dist: fastapi (~=0.85.1)
Requires-Dist: pyjwt (~=2.6.0)
Requires-Dist: deepgram-sdk (==1.0.0)
Requires-Dist: uvicorn (~=0.19.0)
Requires-Dist: slack-sdk (~=3.19.2)
Requires-Dist: pyhumps (~=3.8.0)
